{
    "minimumVersion": 1,
    "serverPushNotifications": true,
    "rateAppAfter": {
        "LevelUp": true,
        "XPPayout": true,
        "VillainCutscene": true
    },
    "maxRPS": 5,
    "logLevel": 2,
    "healthMetricPercentage" : 100,
    "killSwitches": null,
    "msHeartbeat": 1000,
    "fpsHeartbeat": 60,
    "targetPerformance": "LOW",
    "definitionId": 4220002,
    "definitions": "https://eaassets-a.akamaihd.net/cdn-kampai-metadata/rest/def/4220002/definitions",
    "dlcManifests": {
        "med": "LocalManifest/MasterManifestMED",
        "verylow": "LocalManifest/MasterManifestVERYLOW",
        "high": "LocalManifest/MasterManifestHIGH",
        "low": "LocalManifest/MasterManifestLOW"
    },
    "upsightPromoTriggers": [
        {
            "placement": "GameLaunch",
            "enabled": true
        },
        {
            "placement": "Mailbox",
            "enabled": true
        }
    ],
    "allowedVersions" : [ "568", "0", "buildID", "576", "582", "583", "584", "587", "594", "598", "600", "601", "612", "615", "620", "621", "623", "625", "627", "629", "636", "639", "641", "642", "644", "652", "653", "655", "660", "661", "665", "667", "668", "669", "671", "672", "674", "675", "677" ],
  "nudgeUpgradeVersions" : [ "1", "615", "616" ],
  "nudgeUpgradePercentage" : 50
}